rinnaicontrolr/__init__.py
rinnaicontrolr/aws_srp.py
rinnaicontrolr/base.py
rinnaicontrolr/const.py
rinnaicontrolr-0.4.1.dist-info/LICENSE
rinnaicontrolr-0.4.1.dist-info/METADATA
rinnaicontrolr-0.4.1.dist-info/WHEEL
rinnaicontrolr-0.4.1.dist-info/top_level.txt
rinnaicontrolr-0.4.1.dist-info/zip-safe
rinnaicontrolr-0.4.1.dist-info/RECORD
