Metadata-Version: 2.1
Name: rinnaicontrolr
Version: 0.4.1
Summary: Python interface for Rinnai Control-R API
Home-page: https://github.com/explosivo22/rinnaicontrolr
Author: Brad Barbour
Author-email: barbourbj@gmail.com
License: Apache Software License
Keywords: rinnai,home automation,water heater
Classifier: Programming Language :: Python :: 3
Classifier: License :: OSI Approved :: Apache Software License
Classifier: Operating System :: OS Independent
License-File: LICENSE
Requires-Dist: requests (>=2.0)
Requires-Dist: boto3 (>=1.17)
